ormatic/__init__.py
ormatic/custom_types.py
ormatic/dao.py
ormatic/eql_interface.py
ormatic/field_info.py
ormatic/ormatic.py
ormatic/sqlalchemy_generator.py
ormatic/utils.py
ormatic/templates/sqlalchemy_model.py.jinja
ormatic-1.1.16.dist-info/METADATA
ormatic-1.1.16.dist-info/WHEEL
ormatic-1.1.16.dist-info/top_level.txt
ormatic-1.1.16.dist-info/RECORD
