Metadata-Version: 2.4
Name: ormatic
Version: 1.1.16
Summary: Automatic Creation of ORM Models from Python Dataclasses.
Author-email: Tom Schierenbeck <tom_sch@uni-bremen.de>
Project-URL: Source, https://github.com/tomsch420/ormatic
Project-URL: Bug Tracker, https://github.com/tomsch420/ormatic/issues
Keywords: ORM,sqlalchemy,dataclasses,database,models,automatic
Classifier: Programming Language :: Python :: 3
Classifier: License :: OSI Approved :: MIT License
Classifier: Operating System :: OS Independent
Requires-Python: >=3.8
Requires-Dist: sqlalchemy
Requires-Dist: rustworkx
Requires-Dist: jinja2
Requires-Dist: entity_query_language
